means_testing/__init__.py
means_testing/means_testing.py
means_testing-0.0.5.dist-info/METADATA
means_testing-0.0.5.dist-info/WHEEL
means_testing-0.0.5.dist-info/entry_points.txt
means_testing-0.0.5.dist-info/RECORD
