Metadata-Version: 2.4
Name: means-testing
Version: 0.0.5
Summary: A simple library to compare the means of two or more independent samples and check for statistical differences.
Author-email: RenZhen95 <j-liaw@hotmail.com>
Requires-Python: >=3.11
Requires-Dist: numpy>=1.17.3
Requires-Dist: pandas>=2.3.1
Requires-Dist: scipy>=1.16.1
Requires-Dist: seaborn>=0.13.2
